HACKING.rst
LICENSE.txt
MANIFEST.in
README.md
TODO.txt
ez_setup.py
ez_setup_1_4_2.py
setup.cfg
setup.py
nnsuds.egg-info/PKG-INFO
nnsuds.egg-info/SOURCES.txt
nnsuds.egg-info/dependency_links.txt
nnsuds.egg-info/top_level.txt
notes/argument_parsing.rst
notes/readme.txt
notes/traversing_client_data.rst
notes/wsdl_soap_binding.rst
notes/xsd_elements.rst
notes/xsd_types.rst
suds/__init__.py
suds/argparser.py
suds/builder.py
suds/cache.py
suds/client.py
suds/metrics.py
suds/options.py
suds/plugin.py
suds/properties.py
suds/reader.py
suds/resolver.py
suds/servicedefinition.py
suds/serviceproxy.py
suds/soaparray.py
suds/store.py
suds/sudsobject.py
suds/version.py
suds/wsdl.py
suds/wsse.py
suds/bindings/__init__.py
suds/bindings/binding.py
suds/bindings/document.py
suds/bindings/multiref.py
suds/bindings/rpc.py
suds/mx/__init__.py
suds/mx/appender.py
suds/mx/basic.py
suds/mx/core.py
suds/mx/encoded.py
suds/mx/literal.py
suds/mx/typer.py
suds/sax/__init__.py
suds/sax/attribute.py
suds/sax/date.py
suds/sax/document.py
suds/sax/element.py
suds/sax/enc.py
suds/sax/parser.py
suds/sax/text.py
suds/transport/__init__.py
suds/transport/http.py
suds/transport/https.py
suds/transport/options.py
suds/umx/__init__.py
suds/umx/attrlist.py
suds/umx/basic.py
suds/umx/core.py
suds/umx/encoded.py
suds/umx/typed.py
suds/xsd/__init__.py
suds/xsd/depsort.py
suds/xsd/doctor.py
suds/xsd/query.py
suds/xsd/schema.py
suds/xsd/sxbase.py
suds/xsd/sxbasic.py
suds/xsd/sxbuiltin.py
tests/conftest.py
tests/test_argument_parser.py
tests/test_cache.py
tests/test_client.py
tests/test_compare_sax.py
tests/test_date_time.py
tests/test_dependency_sort.py
tests/test_document_store.py
tests/test_input_parameters.py
tests/test_mx.py
tests/test_plugin.py
tests/test_reader.py
tests/test_reply_handling.py
tests/test_request_construction.py
tests/test_sax_document.py
tests/test_sax_element.py
tests/test_sax_encoder.py
tests/test_suds.py
tests/test_timezone.py
tests/test_transport.py
tests/test_transport_http.py
tests/test_wsse.py
tests/test_xsd_builtins.py
tests/test_xsd_element.py
tests/external/__init__.py
tests/external/axis1.py
